pykbi/__init__.py
pykbi/fct.py
pykbi/fscorr.py
pykbi/odf.py
pykbi/rdf.py
pykbi-1.0.0.dist-info/LICENSE
pykbi-1.0.0.dist-info/METADATA
pykbi-1.0.0.dist-info/WHEEL
pykbi-1.0.0.dist-info/top_level.txt
pykbi-1.0.0.dist-info/RECORD
