Metadata-Version: 2.1
Name: pykbi
Version: 1.0.0
Summary: Integrate Radial distribution functions, and calculate Kirkwood-Buff integrals from open and closed systems
Home-page: UNKNOWN
Author: Sondre K. Schnell
Author-email: sondresc@gmail.com
License: UNKNOWN
Keywords: kirkwood-buff integral
Platform: UNKNOWN
Requires-Dist: matplotlib (==2.2.2)
Requires-Dist: numpy (==1.15.0)
Requires-Dist: scipy (==1.1.0)
